dingodb/__init__.py
dingodb/__version__
dingodb/config.py
dingodb/db.py
dingodb/dingo_param.py
dingodb/sdk_client.py
dingodb/common/__init__.py
dingodb/common/constants.py
dingodb/common/document_rep.py
dingodb/common/rawkv_rep.py
dingodb/common/vector_rep.py
dingodb/grpc/__init__.py
dingodb/grpc/grpc_config.py
dingodb/grpc/grpc_db.py
dingodb/grpc/grpc_dingo_param.py
dingodb/grpc/json_format.py
dingodb/protos/__init__.py
dingodb/protos/proxy_common_pb2.py
dingodb/protos/proxy_common_pb2.pyi
dingodb/protos/proxy_common_pb2_grpc.py
dingodb/protos/proxy_error_pb2.py
dingodb/protos/proxy_error_pb2.pyi
dingodb/protos/proxy_error_pb2_grpc.py
dingodb/protos/proxy_index_pb2.py
dingodb/protos/proxy_index_pb2.pyi
dingodb/protos/proxy_index_pb2_grpc.py
dingodb/protos/proxy_meta_pb2.py
dingodb/protos/proxy_meta_pb2.pyi
dingodb/protos/proxy_meta_pb2_grpc.py
dingodb/sdk_document/__init__.py
dingodb/sdk_document/sdk_document_adapter.py
dingodb/sdk_document/sdk_document_client.py
dingodb/sdk_document/sdk_document_db.py
dingodb/sdk_document/sdk_document_param.py
dingodb/sdk_rawkv/__init__.py
dingodb/sdk_rawkv/sdk_rawkv_adapter.py
dingodb/sdk_rawkv/sdk_rawkv_client.py
dingodb/sdk_rawkv/sdk_rawkv_db.py
dingodb/sdk_rawkv/sdk_rawkv_param.py
dingodb/sdk_region_creator/__init__.py
dingodb/sdk_region_creator/sdk_region_creator_adapter.py
dingodb/sdk_region_creator/sdk_region_creator_client.py
dingodb/sdk_region_creator/sdk_region_creator_db.py
dingodb/sdk_region_creator/sdk_region_creator_param.py
dingodb/sdk_vector/__init__.py
dingodb/sdk_vector/sdk_vector_adapter.py
dingodb/sdk_vector/sdk_vector_client.py
dingodb/sdk_vector/sdk_vector_db.py
dingodb/sdk_vector/sdk_vector_param.py
dingodb/sdk_vector/sdk_vector_param_factory.py
dingodb/utils/__init__.py
dingodb/utils/ir.py
dingodb/utils/parser.py
dingodb/utils/tools.py
dingodb-0.3.0.dist-info/LICENSE
dingodb-0.3.0.dist-info/METADATA
dingodb-0.3.0.dist-info/WHEEL
dingodb-0.3.0.dist-info/top_level.txt
dingodb-0.3.0.dist-info/RECORD
