Metadata-Version: 2.1
Name: dingodb
Version: 0.3.0
Summary: dingodb is dingodb sdk
Home-page: https://www.dingodb.com/
Author: DingoDB
Author-email: dingodb@zetyun.com
License: Proprietary License
Project-URL: Homepage, https://www.dingodb.com/
Project-URL: Documentation, https://dingodb.readthedocs.io/en/latest/
Keywords: dingodb
Classifier: Development Status :: 4 - Beta
Classifier: Environment :: Console
Classifier: Environment :: Other Environment
Classifier: Intended Audience :: Developers
Classifier: Intended Audience :: Information Technology
Classifier: Intended Audience :: Science/Research
Classifier: Intended Audience :: System Administrators
Classifier: License :: Other/Proprietary License
Classifier: Operating System :: OS Independent
Classifier: Programming Language :: Python :: 3.7
Classifier: Programming Language :: Python :: 3.8
Classifier: Programming Language :: Python :: 3.9
Classifier: Programming Language :: Python :: 3.10
Classifier: Programming Language :: Python :: 3.11
Classifier: Topic :: Database
Classifier: Topic :: Software Development
Classifier: Topic :: Software Development :: Libraries
Classifier: Topic :: Software Development :: Libraries :: Application Frameworks
Classifier: Topic :: Software Development :: Libraries :: Python Modules
Requires-Python: >=3.7
License-File: LICENSE
Requires-Dist: requests>=2.19.0
Requires-Dist: pydantic
Requires-Dist: pytest>=5.3.4
Requires-Dist: numpy
Requires-Dist: grpcio==1.56.0
Requires-Dist: grpc-gateway-protoc-gen-openapiv2==0.1.0
Requires-Dist: googleapis-common-protos>=1.53.0
Requires-Dist: lz4>=3.1.3
Requires-Dist: protobuf==4.24.0
Requires-Dist: lark
